[
  {
    "node_value": {
      "SingleComment": [
        " main.script",
        [
          1,
          1
        ]
      ]
    },
    "node_next": null,
    "line": 2,
    "column": 1
  },
  {
    "node_value": {
      "Include": "script/test.script"
    },
    "node_next": null,
    "line": 2,
    "column": 9
  },
  {
    "node_value": {
      "String": "script/test.script"
    },
    "node_next": null,
    "line": 3,
    "column": 1
  },
  {
    "node_value": {
      "VariableDeclaration": [
        {
          "node_value": {
            "Variable": "a"
          },
          "node_next": null,
          "line": 3,
          "column": 25
        },
        {
          "node_value": "Empty",
          "node_next": null,
          "line": 3,
          "column": 5
        },
        {
          "node_value": {
            "Array": [
              {
                "node_value": "Empty",
                "node_next": null,
                "line": 3,
                "column": 5
              },
              [
                {
                  "node_value": {
                    "Int": 1000
                  },
                  "node_next": null,
                  "line": 3,
                  "column": 14
                },
                {
                  "node_value": {
                    "Int": 1000
                  },
                  "node_next": null,
                  "line": 3,
                  "column": 19
                },
                {
                  "node_value": {
                    "Int": 1000
                  },
                  "node_next": null,
                  "line": 3,
                  "column": 24
                }
              ]
            ]
          },
          "node_next": null,
          "line": 3,
          "column": 25
        }
      ]
    },
    "node_next": null,
    "line": 3,
    "column": 25
  },
  {
    "node_value": "StatementEnd",
    "node_next": null,
    "line": 3,
    "column": 25
  }
]